foundation/__init__.py
foundation/foundation.py
teleology_foundation-0.0.3.dist-info/LICENSE
teleology_foundation-0.0.3.dist-info/METADATA
teleology_foundation-0.0.3.dist-info/WHEEL
teleology_foundation-0.0.3.dist-info/top_level.txt
teleology_foundation-0.0.3.dist-info/RECORD
