Metadata-Version: 2.1
Name: teleology-foundation
Version: 0.0.3
Summary: Python bindings for the Foundation Api
Author: Foundation
Author-email: support@teleology.io
License: MIT
License-File: LICENSE
Requires-Dist: requests>=2.23.2
Requires-Dist: websocket-client>=1.8.0
